smoothglue/__init__.py
smoothglue/conflictid/__init__.py
smoothglue/conflictid/apps.py
smoothglue/conflictid/migrations/0001_enable_btree_gist.py
smoothglue/conflictid/migrations/0002_initial.py
smoothglue/conflictid/migrations/__init__.py
smoothglue/conflictid/models.py
smoothglue/conflictid/queries.py
smoothglue/conflictid/serializers.py
smoothglue/conflictid/sync.py
smoothglue_conflictid-1.0.0.dist-info/LICENSE
smoothglue_conflictid-1.0.0.dist-info/METADATA
smoothglue_conflictid-1.0.0.dist-info/NOTICE
smoothglue_conflictid-1.0.0.dist-info/WHEEL
smoothglue_conflictid-1.0.0.dist-info/RECORD
