Metadata-Version: 2.3
Name: smoothglue_conflictid
Version: 1.0.0
Summary: A Django app providing high-performance, synchronous deconfliction for scheduling and resource management.
License: Proprietary
Author: BrainGu
Author-email: smoothglue@braingu.com
Requires-Python: >=3.10
Classifier: Programming Language :: Python :: 3
Classifier: Framework :: Django
Classifier: Operating System :: OS Independent
Classifier: Intended Audience :: Developers
Classifier: Topic :: Software Development :: Libraries :: Python Modules
Provides-Extra: dev
Requires-Dist: coverage (>=7.0) ; extra == "dev"
Requires-Dist: django (>=4.2)
Requires-Dist: djangorestframework (>=3.14)
Requires-Dist: psycopg2-binary (>=2.9) ; extra == "dev"
Requires-Dist: pytest-django (>=4.8) ; extra == "dev"
Project-URL: Homepage, https://braingu.com/solutions/smoothglue/
